{
  "url": "https://nextjs.org/",
  "requestedUrl": "https://nextjs.org/",
  "timestamp": 1606716129207,
  "ranks": {
    "hundos": 3,
    "performance": 5,
    "accessibility": 9,
    "cumulative": 3
  },
  "lighthouse": {
    "version": "6.4.1",
    "performance": 0.92,
    "accessibility": 0.97,
    "bestPractices": 1,
    "seo": 1,
    "total": 389
  },
  "firstContentfulPaint": 1965.38,
  "speedIndex": 1965.38,
  "largestContentfulPaint": 2798.07,
  "totalBlockingTime": 251,
  "cumulativeLayoutShift": 0.05105577553643121,
  "timeToInteractive": 3615.8790000000004,
  "maxPotentialFirstInputDelay": 217,
  "timeToFirstByte": 13.414999999999996,
  "weight": {
    "summary": "65 requests • 493 KiB",
    "total": 504526,
    "image": 0,
    "imageCount": 0,
    "script": 219689,
    "scriptCount": 31,
    "document": 46156,
    "font": 37042,
    "fontCount": 1,
    "stylesheet": 2606,
    "stylesheetCount": 1,
    "thirdParty": 95067,
    "thirdPartyCount": 6
  },
  "axe": {
    "passes": 853,
    "violations": 41
  }
}